CHANGELOG.rst
COPYING
LICENSE-ZPL.txt
MANIFEST.in
README.rst
setup.py
tox.ini
zodbtools/__init__.py
zodbtools/help.py
zodbtools/util.py
zodbtools/zodb.py
zodbtools/zodbanalyze.py
zodbtools/zodbcmp.py
zodbtools/zodbcommit.py
zodbtools/zodbdump.py
zodbtools/zodbinfo.py
zodbtools/zodbrestore.py
zodbtools.egg-info/PKG-INFO
zodbtools.egg-info/SOURCES.txt
zodbtools.egg-info/dependency_links.txt
zodbtools.egg-info/entry_points.txt
zodbtools.egg-info/requires.txt
zodbtools.egg-info/top_level.txt
zodbtools/test/__init__.py
zodbtools/test/conftest.py
zodbtools/test/gen_testdata.py
zodbtools/test/test_analyze.py
zodbtools/test/test_commit.py
zodbtools/test/test_dump.py
zodbtools/test/test_restore.py
zodbtools/test/test_tidrange.py
zodbtools/test/test_zodb.py
zodbtools/test/testutil.py
zodbtools/test/testdata/1.fs
zodbtools/test/testdata/1.fs.index
zodbtools/test/testdata/1.zdump.raw.ok
zodbtools/test/testdata/1.zdump.zpickledis.ok
zodbtools/test/testdata/1_!zext.fs
zodbtools/test/testdata/1_!zext.fs.index
zodbtools/test/testdata/1_!zext.zdump.raw.ok
zodbtools/test/testdata/1_!zext.zdump.zpickledis.ok
zodbtools/test/testdata/tid-time-format.txt