Metadata-Version: 2.1
Name: zodbtools
Version: 0.0.0.dev9
Summary: ZODB-related utilities
Home-page: https://lab.nexedi.com/nexedi/zodbtools
Author: Nexedi + Zope Foundation + Community
Author-email: kirr@nexedi.com
License: GPLv3+ with wide exception for Open-Source; ZPL 2.1
Keywords: zodb utility tool
Classifier: Development Status :: 3 - Alpha
Classifier: Intended Audience :: Developers
Classifier: Operating System :: POSIX :: Linux
Classifier: Programming Language :: Python :: 2
Classifier: Programming Language :: Python :: 2.7
Classifier: Topic :: Database
Classifier: Topic :: Utilities
Classifier: Framework :: ZODB
License-File: LICENSE-ZPL.txt
License-File: COPYING
Requires-Dist: ZODB
Requires-Dist: zodburi
Requires-Dist: zope.interface
Requires-Dist: pygolang>=0.0.0.dev6
Requires-Dist: six
Requires-Dist: dateparser
Provides-Extra: test
Requires-Dist: pytest; extra == "test"
Requires-Dist: freezegun; extra == "test"
Requires-Dist: pytz; extra == "test"
Requires-Dist: mock; python_version <= "2.7" and extra == "test"
